pypher/__init__.py
pypher/builder.py
pypher/exception.py
pypher/partial.py
pypher/version.py
pypher/test/__init__.py
pypher/test/builder.py
pypher/test/partial.py
python_cypher-0.20.1.dist-info/LICENSE
python_cypher-0.20.1.dist-info/METADATA
python_cypher-0.20.1.dist-info/WHEEL
python_cypher-0.20.1.dist-info/top_level.txt
python_cypher-0.20.1.dist-info/RECORD
